verisart_verify-0.1.1.data/scripts/verisart-verify
verisartverify/OtsCli.jar
verisartverify/__init__.py
verisartverify/utils.py
verisartverify/verify.py
verisartverify/verify_legacy.py
verisart_verify-0.1.1.dist-info/LICENSE
verisart_verify-0.1.1.dist-info/METADATA
verisart_verify-0.1.1.dist-info/WHEEL
verisart_verify-0.1.1.dist-info/top_level.txt
verisart_verify-0.1.1.dist-info/RECORD
