Metadata-Version: 2.1
Name: verisart-verify
Version: 0.1.1
Summary: Verisart Certificate Verification CLI
Home-page: https://github.com/verisart/verify
Author: Verisart
Author-email: info@verisart.com
License: LGPL
Platform: UNKNOWN
Requires-Dist: requests
Requires-Dist: ecdsa (>=0.16.1)
